gatepoint/__init__.py
gatepoint/__main__.py
gatepoint/errors.py
gatepoint/gateway.py
gatepoint/interaction.py
gatepoint/object_types.py
gatepoint/objects.py
gatepoint/option.py
gatepoint/components/__init__.py
gatepoint/components/button.py
gatepoint/components/menu.py
gatepoint-0.3.dist-info/LICENSE.txt
gatepoint-0.3.dist-info/METADATA
gatepoint-0.3.dist-info/WHEEL
gatepoint-0.3.dist-info/top_level.txt
gatepoint-0.3.dist-info/RECORD
